{
  "updated_at": "2026-04-23T16:36:17.534Z",
  "updated_display": "April 23, 2026",
  "ink": {
    "tvl_millions": 287.1,
    "protocol_count": 26
  },
  "ipo": {
    "polymarket_pct": 76,
    "kalshi_pct": 66,
    "avg_pct": 69.1
  },
  "secondary_market": {
    "hiive_pps": 34.79,
    "forge_pps": 33.25,
    "npm_pps": 37.69,
    "notice_pps": 48.49,
    "avg_pps": 36.01,
    "volume_30d_est_m": 13.5,
    "volume_note": "Est. 30D vol. across all venues · based on Hiive H50 activity",
    "updated": "April 23, 2026"
  },
  "prediction_markets": {
    "ipo": {
      "kalshi_pct": 66,
      "polymarket_pct": 76,
      "mktcap_16b_pct": 71.5,
      "largest_excl_spacex_pct": 4.8
    },
    "underwriters": [
      {
        "bank": "Bank of America",
        "ticker": "BOA",
        "pct": 71.5
      },
      {
        "bank": "Morgan Stanley",
        "ticker": "MS",
        "pct": 63
      },
      {
        "bank": "JPMorgan Chase",
        "ticker": "JPM",
        "pct": 59
      },
      {
        "bank": "Citigroup",
        "ticker": "CITI",
        "pct": 59
      },
      {
        "bank": "Goldman Sachs",
        "ticker": "GS",
        "pct": 57.5
      }
    ],
    "regulatory": {
      "clarity_act_pct": 42.5,
      "crypto_structure_aug_pct": 34.5
    },
    "ink_fdv": {
      "above_250m_pct": 83,
      "above_500m_pct": 66,
      "above_1b_pct": 53.5,
      "above_2b_pct": 17
    }
  }
}
